rad4sea/__init__.py
rad4sea/atmos.py
rad4sea/atmos_dev.ipynb
rad4sea/geom.py
rad4sea/hydros.py
rad4sea/lumos
rad4sea/radio.py
rad4sea/surf.py
rad4sea-0.0.3.dist-info/LICENCE.md
rad4sea-0.0.3.dist-info/METADATA
rad4sea-0.0.3.dist-info/WHEEL
rad4sea-0.0.3.dist-info/top_level.txt
rad4sea-0.0.3.dist-info/RECORD
